PyIRTAM/__init__.py
PyIRTAM/coeff.py
PyIRTAM/lib.py
pyirtam-0.0.6.dist-info/licenses/LICENSE
pyirtam-0.0.6.dist-info/METADATA
pyirtam-0.0.6.dist-info/WHEEL
pyirtam-0.0.6.dist-info/top_level.txt
pyirtam-0.0.6.dist-info/RECORD
