Metadata-Version: 2.4
Name: PyIRTAM
Version: 0.0.6
Summary: Python tool for IRTAM using PyIRI
Author-email: Victoriya Forsythe <victoriya.makarevich@nrl.navy.mil>
License: MIT License
Project-URL: Source, https://github.com/victoriyaforsythe/PyIRTAM
Keywords: ionosphere,modeling,modelling
Classifier: Development Status :: 3 - Alpha
Classifier: Topic :: Scientific/Engineering :: Physics
Classifier: Topic :: Scientific/Engineering :: Atmospheric Science
Classifier: Intended Audience :: Science/Research
Classifier: License :: OSI Approved :: BSD License
Classifier: Natural Language :: English
Classifier: Programming Language :: Python :: 3
Classifier: Programming Language :: Python :: 3.9
Classifier: Programming Language :: Python :: 3.10
Classifier: Programming Language :: Python :: 3.11
Classifier: Operating System :: POSIX :: Linux
Classifier: Operating System :: MacOS :: MacOS X
Classifier: Operating System :: Microsoft :: Windows
Requires-Python: >=3.9
License-File: LICENSE
Requires-Dist: numpy
Requires-Dist: pyiri
Requires-Dist: requests
Provides-Extra: test
Requires-Dist: coveralls; extra == "test"
Requires-Dist: flake8; extra == "test"
Requires-Dist: flake8-docstrings; extra == "test"
Requires-Dist: hacking>=1.0; extra == "test"
Requires-Dist: pytest; extra == "test"
Requires-Dist: pytest-cov; extra == "test"
Requires-Dist: pytest-ordering; extra == "test"
Provides-Extra: doc
Requires-Dist: extras_require; extra == "doc"
Requires-Dist: ipython; extra == "doc"
Requires-Dist: m2r2; extra == "doc"
Requires-Dist: numpydoc; extra == "doc"
Requires-Dist: sphinx; extra == "doc"
Requires-Dist: sphinx_rtd_theme<2.0.0,>=1.2.2; extra == "doc"
Dynamic: license-file
